{"$schema":"http://json-schema.org/draft-06/schema#","$ref":"#/definitions/Welcome2","definitions":{"Welcome2":{"type":"object","additionalProperties":false,"properties":{"type":{"type":"string"},"project_id":{"type":"string"},"private_key_id":{"type":"string"},"private_key":{"type":"string"},"client_email":{"type":"string"},"client_id":{"type":"string"},"auth_uri":{"type":"string","format":"uri","qt-uri-protocols":["https"]},"token_uri":{"type":"string","format":"uri","qt-uri-protocols":["https"]},"auth_provider_x509_cert_url":{"type":"string","format":"uri","qt-uri-protocols":["https"]},"client_x509_cert_url":{"type":"string","format":"uri","qt-uri-protocols":["https"],"qt-uri-extensions":[".com"]},"universe_domain":{"type":"string"}},"required":["auth_provider_x509_cert_url","auth_uri","client_email","client_id","client_x509_cert_url","private_key","private_key_id","project_id","token_uri","type","universe_domain"],"title":"Welcome2"}}}